mcp_ad_server/__init__.py
mcp_ad_server/config.py
mcp_ad_server/main.py
mcp_ad_server/data/groups/1_投放启动决策指标组.json
mcp_ad_server/data/groups/2_投放效果实时监控指标组.json
mcp_ad_server/data/groups/3_短期价值评估指标组(首日-7日).json
mcp_ad_server/data/groups/4_深度价值与留存指标组.json
mcp_ad_server/data/groups/5_平台数据对账指标组.json
mcp_ad_server/data/groups/6_终止决策预警指标组.json
mcp_ad_server/data/groups/7_财务核算指标组.json
mcp_ad_server/data/indicators/card_games/ad.json
mcp_ad_server/data/indicators/card_games/material.json
mcp_ad_server/data/indicators/definitions/24小时ROI.json
mcp_ad_server/data/indicators/definitions/3秒播放率.json
mcp_ad_server/data/indicators/definitions/7日ROI.json
mcp_ad_server/data/indicators/definitions/cid.json
mcp_ad_server/data/indicators/definitions/cid备注.json
mcp_ad_server/data/indicators/definitions/一键起量消耗.json
mcp_ad_server/data/indicators/definitions/一阶段花费.json
mcp_ad_server/data/indicators/definitions/二阶段花费.json
mcp_ad_server/data/indicators/definitions/付费分成后累计ROI.json
mcp_ad_server/data/indicators/definitions/付费分成后首日ROI.json
mcp_ad_server/data/indicators/definitions/付费成本.json
mcp_ad_server/data/indicators/definitions/付费用户平均关卡.json
mcp_ad_server/data/indicators/definitions/付费用户平均在线时长（分钟）.json
mcp_ad_server/data/indicators/definitions/付费用户平均章节.json
mcp_ad_server/data/indicators/definitions/付费累计ROI.json
mcp_ad_server/data/indicators/definitions/付费首日ROI.json
mcp_ad_server/data/indicators/definitions/优质广告状态.json
mcp_ad_server/data/indicators/definitions/低质原因.json
mcp_ad_server/data/indicators/definitions/分成后累计ROI.json
mcp_ad_server/data/indicators/definitions/分成后累计平台ROI.json
mcp_ad_server/data/indicators/definitions/分成后首日ROI.json
mcp_ad_server/data/indicators/definitions/分成后首日平台ROI.json
mcp_ad_server/data/indicators/definitions/创意人.json
mcp_ad_server/data/indicators/definitions/创意名称.json
mcp_ad_server/data/indicators/definitions/创角成本.json
mcp_ad_server/data/indicators/definitions/创角率.json
mcp_ad_server/data/indicators/definitions/制作人.json
mcp_ad_server-0.0.13.dist-info/METADATA
mcp_ad_server-0.0.13.dist-info/WHEEL
mcp_ad_server-0.0.13.dist-info/entry_points.txt
mcp_ad_server-0.0.13.dist-info/top_level.txt
mcp_ad_server-0.0.13.dist-info/RECORD
