Metadata-Version: 2.4
Name: mcp-ad-server
Version: 0.0.13
Summary: MCP服务器用于处理广告投放数据
Author-email: 江厚望 <jianghouwang@dartou.com>, 邓嘉豪 <dengjiahao@dartou.com>, 刘松奇 <liusongqi@dartou.com>
Maintainer-email: 江厚望 <jianghouwang@dartou.com>
License: MIT
Keywords: mcp,advertising,analytics,data-analysis
Classifier: Development Status :: 4 - Beta
Classifier: Intended Audience :: Developers
Classifier: License :: OSI Approved :: MIT License
Classifier: Programming Language :: Python :: 3
Classifier: Programming Language :: Python :: 3 :: Only
Classifier: Programming Language :: Python :: 3.11
Classifier: Programming Language :: Python :: 3.12
Requires-Python: >=3.11
Requires-Dist: mcp>=1.2.0
Requires-Dist: httpx[socks]>=0.25.0
Requires-Dist: aiofiles>=23.0.0
Requires-Dist: python-dateutil>=2.8.0
Requires-Dist: python-dotenv>=1.0.0
Requires-Dist: pydantic>=2.7.0
Provides-Extra: dev
Requires-Dist: pytest>=7.4.0; extra == "dev"
Requires-Dist: pytest-asyncio>=0.21.0; extra == "dev"
Requires-Dist: pytest-cov>=4.1.0; extra == "dev"
Requires-Dist: black>=23.12.0; extra == "dev"
Requires-Dist: isort>=5.13.0; extra == "dev"
Requires-Dist: ruff>=0.1.9; extra == "dev"
Requires-Dist: mypy>=1.8.0; extra == "dev"
Requires-Dist: pre-commit>=3.6.0; extra == "dev"
Provides-Extra: monitoring
Requires-Dist: prometheus-client>=0.19.0; extra == "monitoring"
Provides-Extra: cache
Requires-Dist: redis>=5.0.0; extra == "cache"
Provides-Extra: docs
Requires-Dist: mkdocs>=1.5.0; extra == "docs"
Requires-Dist: mkdocs-material>=9.4.0; extra == "docs"
Requires-Dist: mkdocstrings[python]>=0.24.0; extra == "docs"
